<annotation>
  <folder>NA</folder>
  <filename>2016-04-30-13-28-45_WBB6__DelancyClinton.jpg</filename>
  <size>
    <width>352</width>
    <height>240</height>
    <depth>0</depth>
  </size>
  <segmented>0</segmented>
  <object>
    <name>pos</name>
    <pose>NA</pose>
    <truncated>0</truncated>
    <difficult>0</difficult>
    <bndbox>
      <xmin>22</xmin>
      <ymin>154</ymin>
      <xmax>33</xmax>
      <ymax>169</ymax>
    </bndbox>
  </object>
  <object>
    <name>pos</name>
    <pose>NA</pose>
    <truncated>0</truncated>
    <difficult>0</difficult>
    <bndbox>
      <xmin>36</xmin>
      <ymin>149</ymin>
      <xmax>48</xmax>
      <ymax>164</ymax>
    </bndbox>
  </object>
  <object>
    <name>pos</name>
    <pose>NA</pose>
    <truncated>0</truncated>
    <difficult>0</difficult>
    <bndbox>
      <xmin>42</xmin>
      <ymin>148</ymin>
      <xmax>53</xmax>
      <ymax>162</ymax>
    </bndbox>
  </object>
  <object>
    <name>neg</name>
    <pose>NA</pose>
    <truncated>0</truncated>
    <difficult>0</difficult>
    <bndbox>
      <xmin>71</xmin>
      <ymin>141</ymin>
      <xmax>80</xmax>
      <ymax>154</ymax>
    </bndbox>
  </object>
  <object>
    <name>neg</name>
    <pose>NA</pose>
    <truncated>0</truncated>
    <difficult>0</difficult>
    <bndbox>
      <xmin>88</xmin>
      <ymin>163</ymin>
      <xmax>98</xmax>
      <ymax>176</ymax>
    </bndbox>
  </object>
  <object>
    <name>neg</name>
    <pose>NA</pose>
    <truncated>0</truncated>
    <difficult>0</difficult>
    <bndbox>
      <xmin>34</xmin>
      <ymin>173</ymin>
      <xmax>47</xmax>
      <ymax>190</ymax>
    </bndbox>
  </object>
  <object>
    <name>neg</name>
    <pose>NA</pose>
    <truncated>0</truncated>
    <difficult>0</difficult>
    <bndbox>
      <xmin>144</xmin>
      <ymin>29</ymin>
      <xmax>153</xmax>
      <ymax>42</ymax>
    </bndbox>
  </object>
  <object>
    <name>neg</name>
    <pose>NA</pose>
    <truncated>0</truncated>
    <difficult>0</difficult>
    <bndbox>
      <xmin>192</xmin>
      <ymin>106</ymin>
      <xmax>201</xmax>
      <ymax>118</ymax>
    </bndbox>
  </object>
  <object>
    <name>neg</name>
    <pose>NA</pose>
    <truncated>0</truncated>
    <difficult>0</difficult>
    <bndbox>
      <xmin>236</xmin>
      <ymin>107</ymin>
      <xmax>247</xmax>
      <ymax>122</ymax>
    </bndbox>
  </object>
  <object>
    <name>neg</name>
    <pose>NA</pose>
    <truncated>0</truncated>
    <difficult>0</difficult>
    <bndbox>
      <xmin>158</xmin>
      <ymin>95</ymin>
      <xmax>174</xmax>
      <ymax>116</ymax>
    </bndbox>
  </object>
  <object>
    <name>neg</name>
    <pose>NA</pose>
    <truncated>0</truncated>
    <difficult>0</difficult>
    <bndbox>
      <xmin>232</xmin>
      <ymin>195</ymin>
      <xmax>248</xmax>
      <ymax>217</ymax>
    </bndbox>
  </object>
  <object>
    <name>neg</name>
    <pose>NA</pose>
    <truncated>0</truncated>
    <difficult>0</difficult>
    <bndbox>
      <xmin>122</xmin>
      <ymin>193</ymin>
      <xmax>141</xmax>
      <ymax>219</ymax>
    </bndbox>
  </object>
</annotation>
