<annotation>
  <folder>NA</folder>
  <filename>2016-06-19-20-26-05_Grand_St__Essex_St.jpg</filename>
  <size>
    <width>352</width>
    <height>240</height>
    <depth>0</depth>
  </size>
  <segmented>0</segmented>
  <object>
    <name>pos</name>
    <pose>NA</pose>
    <truncated>0</truncated>
    <difficult>0</difficult>
    <bndbox>
      <xmin>158</xmin>
      <ymin>131</ymin>
      <xmax>186</xmax>
      <ymax>167</ymax>
    </bndbox>
  </object>
  <object>
    <name>neg</name>
    <pose>NA</pose>
    <truncated>0</truncated>
    <difficult>0</difficult>
    <bndbox>
      <xmin>258</xmin>
      <ymin>110</ymin>
      <xmax>287</xmax>
      <ymax>149</ymax>
    </bndbox>
  </object>
  <object>
    <name>neg</name>
    <pose>NA</pose>
    <truncated>0</truncated>
    <difficult>0</difficult>
    <bndbox>
      <xmin>270</xmin>
      <ymin>68</ymin>
      <xmax>288</xmax>
      <ymax>91</ymax>
    </bndbox>
  </object>
  <object>
    <name>neg</name>
    <pose>NA</pose>
    <truncated>0</truncated>
    <difficult>0</difficult>
    <bndbox>
      <xmin>297</xmin>
      <ymin>63</ymin>
      <xmax>312</xmax>
      <ymax>83</ymax>
    </bndbox>
  </object>
</annotation>
