<annotation>
  <folder>NA</folder>
  <filename>2016-04-30-16-21-37_Amsterdam__86_St.jpg</filename>
  <size>
    <width>352</width>
    <height>240</height>
    <depth>0</depth>
  </size>
  <segmented>0</segmented>
  <object>
    <name>neg</name>
    <pose>NA</pose>
    <truncated>0</truncated>
    <difficult>0</difficult>
    <bndbox>
      <xmin>230</xmin>
      <ymin>169</ymin>
      <xmax>250</xmax>
      <ymax>195</ymax>
    </bndbox>
  </object>
  <object>
    <name>neg</name>
    <pose>NA</pose>
    <truncated>0</truncated>
    <difficult>0</difficult>
    <bndbox>
      <xmin>112</xmin>
      <ymin>146</ymin>
      <xmax>168</xmax>
      <ymax>220</ymax>
    </bndbox>
  </object>
  <object>
    <name>neg</name>
    <pose>NA</pose>
    <truncated>0</truncated>
    <difficult>0</difficult>
    <bndbox>
      <xmin>194</xmin>
      <ymin>84</ymin>
      <xmax>204</xmax>
      <ymax>98</ymax>
    </bndbox>
  </object>
  <object>
    <name>neg</name>
    <pose>NA</pose>
    <truncated>0</truncated>
    <difficult>0</difficult>
    <bndbox>
      <xmin>185</xmin>
      <ymin>78</ymin>
      <xmax>198</xmax>
      <ymax>95</ymax>
    </bndbox>
  </object>
  <object>
    <name>neg</name>
    <pose>NA</pose>
    <truncated>0</truncated>
    <difficult>0</difficult>
    <bndbox>
      <xmin>175</xmin>
      <ymin>105</ymin>
      <xmax>186</xmax>
      <ymax>120</ymax>
    </bndbox>
  </object>
  <object>
    <name>neg</name>
    <pose>NA</pose>
    <truncated>0</truncated>
    <difficult>0</difficult>
    <bndbox>
      <xmin>154</xmin>
      <ymin>124</ymin>
      <xmax>166</xmax>
      <ymax>142</ymax>
    </bndbox>
  </object>
  <object>
    <name>neg</name>
    <pose>NA</pose>
    <truncated>0</truncated>
    <difficult>0</difficult>
    <bndbox>
      <xmin>203</xmin>
      <ymin>138</ymin>
      <xmax>224</xmax>
      <ymax>166</ymax>
    </bndbox>
  </object>
</annotation>
