<annotation>
  <folder>NA</folder>
  <filename>2016-06-19-19-38-34_Madison_Ave__42_St.jpg</filename>
  <size>
    <width>352</width>
    <height>240</height>
    <depth>0</depth>
  </size>
  <segmented>0</segmented>
  <object>
    <name>pos</name>
    <pose>NA</pose>
    <truncated>0</truncated>
    <difficult>0</difficult>
    <bndbox>
      <xmin>147</xmin>
      <ymin>164</ymin>
      <xmax>169</xmax>
      <ymax>193</ymax>
    </bndbox>
  </object>
  <object>
    <name>pos</name>
    <pose>NA</pose>
    <truncated>0</truncated>
    <difficult>0</difficult>
    <bndbox>
      <xmin>148</xmin>
      <ymin>152</ymin>
      <xmax>159</xmax>
      <ymax>167</ymax>
    </bndbox>
  </object>
  <object>
    <name>pos</name>
    <pose>NA</pose>
    <truncated>0</truncated>
    <difficult>0</difficult>
    <bndbox>
      <xmin>122</xmin>
      <ymin>186</ymin>
      <xmax>154</xmax>
      <ymax>227</ymax>
    </bndbox>
  </object>
  <object>
    <name>pos</name>
    <pose>NA</pose>
    <truncated>0</truncated>
    <difficult>0</difficult>
    <bndbox>
      <xmin>133</xmin>
      <ymin>171</ymin>
      <xmax>147</xmax>
      <ymax>188</ymax>
    </bndbox>
  </object>
  <object>
    <name>pos</name>
    <pose>NA</pose>
    <truncated>0</truncated>
    <difficult>0</difficult>
    <bndbox>
      <xmin>69</xmin>
      <ymin>189</ymin>
      <xmax>103</xmax>
      <ymax>234</ymax>
    </bndbox>
  </object>
  <object>
    <name>pos</name>
    <pose>NA</pose>
    <truncated>0</truncated>
    <difficult>0</difficult>
    <bndbox>
      <xmin>57</xmin>
      <ymin>212</ymin>
      <xmax>77</xmax>
      <ymax>239</ymax>
    </bndbox>
  </object>
  <object>
    <name>neg</name>
    <pose>NA</pose>
    <truncated>0</truncated>
    <difficult>0</difficult>
    <bndbox>
      <xmin>108</xmin>
      <ymin>39</ymin>
      <xmax>121</xmax>
      <ymax>56</ymax>
    </bndbox>
  </object>
  <object>
    <name>neg</name>
    <pose>NA</pose>
    <truncated>0</truncated>
    <difficult>0</difficult>
    <bndbox>
      <xmin>72</xmin>
      <ymin>34</ymin>
      <xmax>82</xmax>
      <ymax>48</ymax>
    </bndbox>
  </object>
  <object>
    <name>neg</name>
    <pose>NA</pose>
    <truncated>0</truncated>
    <difficult>0</difficult>
    <bndbox>
      <xmin>329</xmin>
      <ymin>126</ymin>
      <xmax>346</xmax>
      <ymax>148</ymax>
    </bndbox>
  </object>
</annotation>
