<annotation>
  <folder>NA</folder>
  <filename>2016-04-30-16-49-00_6_Ave__West_Houston_St.jpg</filename>
  <size>
    <width>352</width>
    <height>240</height>
    <depth>0</depth>
  </size>
  <segmented>0</segmented>
  <object>
    <name>pos</name>
    <pose>NA</pose>
    <truncated>0</truncated>
    <difficult>0</difficult>
    <bndbox>
      <xmin>27</xmin>
      <ymin>87</ymin>
      <xmax>55</xmax>
      <ymax>124</ymax>
    </bndbox>
  </object>
  <object>
    <name>pos</name>
    <pose>NA</pose>
    <truncated>0</truncated>
    <difficult>0</difficult>
    <bndbox>
      <xmin>143</xmin>
      <ymin>98</ymin>
      <xmax>169</xmax>
      <ymax>132</ymax>
    </bndbox>
  </object>
  <object>
    <name>pos</name>
    <pose>NA</pose>
    <truncated>0</truncated>
    <difficult>0</difficult>
    <bndbox>
      <xmin>336</xmin>
      <ymin>82</ymin>
      <xmax>351</xmax>
      <ymax>111</ymax>
    </bndbox>
  </object>
  <object>
    <name>pos</name>
    <pose>NA</pose>
    <truncated>0</truncated>
    <difficult>0</difficult>
    <bndbox>
      <xmin>51</xmin>
      <ymin>36</ymin>
      <xmax>64</xmax>
      <ymax>54</ymax>
    </bndbox>
  </object>
  <object>
    <name>pos</name>
    <pose>NA</pose>
    <truncated>0</truncated>
    <difficult>0</difficult>
    <bndbox>
      <xmin>41</xmin>
      <ymin>42</ymin>
      <xmax>51</xmax>
      <ymax>56</ymax>
    </bndbox>
  </object>
  <object>
    <name>pos</name>
    <pose>NA</pose>
    <truncated>0</truncated>
    <difficult>0</difficult>
    <bndbox>
      <xmin>72</xmin>
      <ymin>30</ymin>
      <xmax>81</xmax>
      <ymax>42</ymax>
    </bndbox>
  </object>
  <object>
    <name>pos</name>
    <pose>NA</pose>
    <truncated>0</truncated>
    <difficult>0</difficult>
    <bndbox>
      <xmin>67</xmin>
      <ymin>28</ymin>
      <xmax>75</xmax>
      <ymax>39</ymax>
    </bndbox>
  </object>
  <object>
    <name>pos</name>
    <pose>NA</pose>
    <truncated>0</truncated>
    <difficult>0</difficult>
    <bndbox>
      <xmin>84</xmin>
      <ymin>26</ymin>
      <xmax>96</xmax>
      <ymax>41</ymax>
    </bndbox>
  </object>
  <object>
    <name>neg</name>
    <pose>NA</pose>
    <truncated>0</truncated>
    <difficult>0</difficult>
    <bndbox>
      <xmin>50</xmin>
      <ymin>92</ymin>
      <xmax>81</xmax>
      <ymax>133</ymax>
    </bndbox>
  </object>
  <object>
    <name>neg</name>
    <pose>NA</pose>
    <truncated>0</truncated>
    <difficult>0</difficult>
    <bndbox>
      <xmin>158</xmin>
      <ymin>20</ymin>
      <xmax>180</xmax>
      <ymax>50</ymax>
    </bndbox>
  </object>
  <object>
    <name>neg</name>
    <pose>NA</pose>
    <truncated>0</truncated>
    <difficult>0</difficult>
    <bndbox>
      <xmin>191</xmin>
      <ymin>36</ymin>
      <xmax>207</xmax>
      <ymax>57</ymax>
    </bndbox>
  </object>
  <object>
    <name>neg</name>
    <pose>NA</pose>
    <truncated>0</truncated>
    <difficult>0</difficult>
    <bndbox>
      <xmin>214</xmin>
      <ymin>36</ymin>
      <xmax>227</xmax>
      <ymax>54</ymax>
    </bndbox>
  </object>
  <object>
    <name>neg</name>
    <pose>NA</pose>
    <truncated>0</truncated>
    <difficult>0</difficult>
    <bndbox>
      <xmin>243</xmin>
      <ymin>41</ymin>
      <xmax>258</xmax>
      <ymax>61</ymax>
    </bndbox>
  </object>
  <object>
    <name>neg</name>
    <pose>NA</pose>
    <truncated>0</truncated>
    <difficult>0</difficult>
    <bndbox>
      <xmin>113</xmin>
      <ymin>44</ymin>
      <xmax>129</xmax>
      <ymax>66</ymax>
    </bndbox>
  </object>
  <object>
    <name>neg</name>
    <pose>NA</pose>
    <truncated>0</truncated>
    <difficult>0</difficult>
    <bndbox>
      <xmin>74</xmin>
      <ymin>56</ymin>
      <xmax>91</xmax>
      <ymax>79</ymax>
    </bndbox>
  </object>
</annotation>
