<annotation>
  <folder>NA</folder>
  <filename>2016-04-30-13-32-25_Madison_Ave__42_St.jpg</filename>
  <size>
    <width>352</width>
    <height>240</height>
    <depth>0</depth>
  </size>
  <segmented>0</segmented>
  <object>
    <name>pos</name>
    <pose>NA</pose>
    <truncated>0</truncated>
    <difficult>0</difficult>
    <bndbox>
      <xmin>292</xmin>
      <ymin>183</ymin>
      <xmax>329</xmax>
      <ymax>233</ymax>
    </bndbox>
  </object>
  <object>
    <name>pos</name>
    <pose>NA</pose>
    <truncated>0</truncated>
    <difficult>0</difficult>
    <bndbox>
      <xmin>207</xmin>
      <ymin>213</ymin>
      <xmax>225</xmax>
      <ymax>238</ymax>
    </bndbox>
  </object>
  <object>
    <name>pos</name>
    <pose>NA</pose>
    <truncated>0</truncated>
    <difficult>0</difficult>
    <bndbox>
      <xmin>173</xmin>
      <ymin>200</ymin>
      <xmax>202</xmax>
      <ymax>237</ymax>
    </bndbox>
  </object>
  <object>
    <name>pos</name>
    <pose>NA</pose>
    <truncated>0</truncated>
    <difficult>0</difficult>
    <bndbox>
      <xmin>160</xmin>
      <ymin>210</ymin>
      <xmax>180</xmax>
      <ymax>237</ymax>
    </bndbox>
  </object>
  <object>
    <name>pos</name>
    <pose>NA</pose>
    <truncated>0</truncated>
    <difficult>0</difficult>
    <bndbox>
      <xmin>130</xmin>
      <ymin>171</ymin>
      <xmax>170</xmax>
      <ymax>225</ymax>
    </bndbox>
  </object>
  <object>
    <name>pos</name>
    <pose>NA</pose>
    <truncated>0</truncated>
    <difficult>0</difficult>
    <bndbox>
      <xmin>121</xmin>
      <ymin>179</ymin>
      <xmax>156</xmax>
      <ymax>227</ymax>
    </bndbox>
  </object>
  <object>
    <name>pos</name>
    <pose>NA</pose>
    <truncated>0</truncated>
    <difficult>0</difficult>
    <bndbox>
      <xmin>116</xmin>
      <ymin>195</ymin>
      <xmax>144</xmax>
      <ymax>234</ymax>
    </bndbox>
  </object>
  <object>
    <name>pos</name>
    <pose>NA</pose>
    <truncated>0</truncated>
    <difficult>0</difficult>
    <bndbox>
      <xmin>97</xmin>
      <ymin>190</ymin>
      <xmax>127</xmax>
      <ymax>230</ymax>
    </bndbox>
  </object>
  <object>
    <name>pos</name>
    <pose>NA</pose>
    <truncated>0</truncated>
    <difficult>0</difficult>
    <bndbox>
      <xmin>93</xmin>
      <ymin>229</ymin>
      <xmax>100</xmax>
      <ymax>239</ymax>
    </bndbox>
  </object>
  <object>
    <name>pos</name>
    <pose>NA</pose>
    <truncated>0</truncated>
    <difficult>0</difficult>
    <bndbox>
      <xmin>253</xmin>
      <ymin>52</ymin>
      <xmax>261</xmax>
      <ymax>62</ymax>
    </bndbox>
  </object>
  <object>
    <name>neg</name>
    <pose>NA</pose>
    <truncated>0</truncated>
    <difficult>0</difficult>
    <bndbox>
      <xmin>216</xmin>
      <ymin>120</ymin>
      <xmax>233</xmax>
      <ymax>142</ymax>
    </bndbox>
  </object>
  <object>
    <name>neg</name>
    <pose>NA</pose>
    <truncated>0</truncated>
    <difficult>0</difficult>
    <bndbox>
      <xmin>152</xmin>
      <ymin>53</ymin>
      <xmax>182</xmax>
      <ymax>94</ymax>
    </bndbox>
  </object>
  <object>
    <name>neg</name>
    <pose>NA</pose>
    <truncated>0</truncated>
    <difficult>0</difficult>
    <bndbox>
      <xmin>215</xmin>
      <ymin>69</ymin>
      <xmax>234</xmax>
      <ymax>93</ymax>
    </bndbox>
  </object>
  <object>
    <name>neg</name>
    <pose>NA</pose>
    <truncated>0</truncated>
    <difficult>0</difficult>
    <bndbox>
      <xmin>140</xmin>
      <ymin>118</ymin>
      <xmax>156</xmax>
      <ymax>140</ymax>
    </bndbox>
  </object>
  <object>
    <name>neg</name>
    <pose>NA</pose>
    <truncated>0</truncated>
    <difficult>0</difficult>
    <bndbox>
      <xmin>187</xmin>
      <ymin>123</ymin>
      <xmax>198</xmax>
      <ymax>138</ymax>
    </bndbox>
  </object>
  <object>
    <name>neg</name>
    <pose>NA</pose>
    <truncated>0</truncated>
    <difficult>0</difficult>
    <bndbox>
      <xmin>276</xmin>
      <ymin>112</ymin>
      <xmax>288</xmax>
      <ymax>128</ymax>
    </bndbox>
  </object>
  <object>
    <name>neg</name>
    <pose>NA</pose>
    <truncated>0</truncated>
    <difficult>0</difficult>
    <bndbox>
      <xmin>317</xmin>
      <ymin>78</ymin>
      <xmax>333</xmax>
      <ymax>100</ymax>
    </bndbox>
  </object>
  <object>
    <name>neg</name>
    <pose>NA</pose>
    <truncated>0</truncated>
    <difficult>0</difficult>
    <bndbox>
      <xmin>281</xmin>
      <ymin>69</ymin>
      <xmax>298</xmax>
      <ymax>92</ymax>
    </bndbox>
  </object>
  <object>
    <name>neg</name>
    <pose>NA</pose>
    <truncated>0</truncated>
    <difficult>0</difficult>
    <bndbox>
      <xmin>301</xmin>
      <ymin>51</ymin>
      <xmax>307</xmax>
      <ymax>60</ymax>
    </bndbox>
  </object>
  <object>
    <name>neg</name>
    <pose>NA</pose>
    <truncated>0</truncated>
    <difficult>0</difficult>
    <bndbox>
      <xmin>282</xmin>
      <ymin>25</ymin>
      <xmax>293</xmax>
      <ymax>40</ymax>
    </bndbox>
  </object>
  <object>
    <name>neg</name>
    <pose>NA</pose>
    <truncated>0</truncated>
    <difficult>0</difficult>
    <bndbox>
      <xmin>204</xmin>
      <ymin>24</ymin>
      <xmax>224</xmax>
      <ymax>51</ymax>
    </bndbox>
  </object>
  <object>
    <name>neg</name>
    <pose>NA</pose>
    <truncated>0</truncated>
    <difficult>0</difficult>
    <bndbox>
      <xmin>125</xmin>
      <ymin>23</ymin>
      <xmax>135</xmax>
      <ymax>36</ymax>
    </bndbox>
  </object>
  <object>
    <name>neg</name>
    <pose>NA</pose>
    <truncated>0</truncated>
    <difficult>0</difficult>
    <bndbox>
      <xmin>44</xmin>
      <ymin>38</ymin>
      <xmax>64</xmax>
      <ymax>64</ymax>
    </bndbox>
  </object>
  <object>
    <name>neg</name>
    <pose>NA</pose>
    <truncated>0</truncated>
    <difficult>0</difficult>
    <bndbox>
      <xmin>97</xmin>
      <ymin>56</ymin>
      <xmax>114</xmax>
      <ymax>78</ymax>
    </bndbox>
  </object>
  <object>
    <name>neg</name>
    <pose>NA</pose>
    <truncated>0</truncated>
    <difficult>0</difficult>
    <bndbox>
      <xmin>34</xmin>
      <ymin>91</ymin>
      <xmax>50</xmax>
      <ymax>113</ymax>
    </bndbox>
  </object>
  <object>
    <name>neg</name>
    <pose>NA</pose>
    <truncated>0</truncated>
    <difficult>0</difficult>
    <bndbox>
      <xmin>82</xmin>
      <ymin>106</ymin>
      <xmax>92</xmax>
      <ymax>120</ymax>
    </bndbox>
  </object>
  <object>
    <name>neg</name>
    <pose>NA</pose>
    <truncated>0</truncated>
    <difficult>0</difficult>
    <bndbox>
      <xmin>54</xmin>
      <ymin>142</ymin>
      <xmax>67</xmax>
      <ymax>160</ymax>
    </bndbox>
  </object>
  <object>
    <name>neg</name>
    <pose>NA</pose>
    <truncated>0</truncated>
    <difficult>0</difficult>
    <bndbox>
      <xmin>109</xmin>
      <ymin>143</ymin>
      <xmax>116</xmax>
      <ymax>153</ymax>
    </bndbox>
  </object>
  <object>
    <name>neg</name>
    <pose>NA</pose>
    <truncated>0</truncated>
    <difficult>0</difficult>
    <bndbox>
      <xmin>48</xmin>
      <ymin>178</ymin>
      <xmax>73</xmax>
      <ymax>210</ymax>
    </bndbox>
  </object>
  <object>
    <name>neg</name>
    <pose>NA</pose>
    <truncated>0</truncated>
    <difficult>0</difficult>
    <bndbox>
      <xmin>231</xmin>
      <ymin>171</ymin>
      <xmax>250</xmax>
      <ymax>196</ymax>
    </bndbox>
  </object>
  <object>
    <name>neg</name>
    <pose>NA</pose>
    <truncated>0</truncated>
    <difficult>0</difficult>
    <bndbox>
      <xmin>183</xmin>
      <ymin>151</ymin>
      <xmax>199</xmax>
      <ymax>172</ymax>
    </bndbox>
  </object>
  <object>
    <name>neg</name>
    <pose>NA</pose>
    <truncated>0</truncated>
    <difficult>0</difficult>
    <bndbox>
      <xmin>290</xmin>
      <ymin>147</ymin>
      <xmax>306</xmax>
      <ymax>168</ymax>
    </bndbox>
  </object>
  <object>
    <name>neg</name>
    <pose>NA</pose>
    <truncated>0</truncated>
    <difficult>0</difficult>
    <bndbox>
      <xmin>335</xmin>
      <ymin>148</ymin>
      <xmax>351</xmax>
      <ymax>175</ymax>
    </bndbox>
  </object>
</annotation>
