<annotation>
  <folder>NA</folder>
  <filename>2016-04-30-13-38-02_Worth_Street__W_Broadway.jpg</filename>
  <size>
    <width>352</width>
    <height>240</height>
    <depth>0</depth>
  </size>
  <segmented>0</segmented>
  <object>
    <name>pos</name>
    <pose>NA</pose>
    <truncated>0</truncated>
    <difficult>0</difficult>
    <bndbox>
      <xmin>299</xmin>
      <ymin>92</ymin>
      <xmax>319</xmax>
      <ymax>119</ymax>
    </bndbox>
  </object>
  <object>
    <name>pos</name>
    <pose>NA</pose>
    <truncated>0</truncated>
    <difficult>0</difficult>
    <bndbox>
      <xmin>270</xmin>
      <ymin>74</ymin>
      <xmax>288</xmax>
      <ymax>98</ymax>
    </bndbox>
  </object>
  <object>
    <name>pos</name>
    <pose>NA</pose>
    <truncated>0</truncated>
    <difficult>0</difficult>
    <bndbox>
      <xmin>216</xmin>
      <ymin>66</ymin>
      <xmax>228</xmax>
      <ymax>82</ymax>
    </bndbox>
  </object>
  <object>
    <name>pos</name>
    <pose>NA</pose>
    <truncated>0</truncated>
    <difficult>0</difficult>
    <bndbox>
      <xmin>173</xmin>
      <ymin>54</ymin>
      <xmax>183</xmax>
      <ymax>68</ymax>
    </bndbox>
  </object>
  <object>
    <name>pos</name>
    <pose>NA</pose>
    <truncated>0</truncated>
    <difficult>0</difficult>
    <bndbox>
      <xmin>168</xmin>
      <ymin>55</ymin>
      <xmax>177</xmax>
      <ymax>68</ymax>
    </bndbox>
  </object>
  <object>
    <name>pos</name>
    <pose>NA</pose>
    <truncated>0</truncated>
    <difficult>0</difficult>
    <bndbox>
      <xmin>140</xmin>
      <ymin>47</ymin>
      <xmax>150</xmax>
      <ymax>59</ymax>
    </bndbox>
  </object>
  <object>
    <name>pos</name>
    <pose>NA</pose>
    <truncated>0</truncated>
    <difficult>0</difficult>
    <bndbox>
      <xmin>150</xmin>
      <ymin>51</ymin>
      <xmax>159</xmax>
      <ymax>63</ymax>
    </bndbox>
  </object>
  <object>
    <name>neg</name>
    <pose>NA</pose>
    <truncated>0</truncated>
    <difficult>0</difficult>
    <bndbox>
      <xmin>103</xmin>
      <ymin>45</ymin>
      <xmax>115</xmax>
      <ymax>61</ymax>
    </bndbox>
  </object>
  <object>
    <name>neg</name>
    <pose>NA</pose>
    <truncated>0</truncated>
    <difficult>0</difficult>
    <bndbox>
      <xmin>70</xmin>
      <ymin>49</ymin>
      <xmax>82</xmax>
      <ymax>64</ymax>
    </bndbox>
  </object>
  <object>
    <name>neg</name>
    <pose>NA</pose>
    <truncated>0</truncated>
    <difficult>0</difficult>
    <bndbox>
      <xmin>100</xmin>
      <ymin>80</ymin>
      <xmax>121</xmax>
      <ymax>108</ymax>
    </bndbox>
  </object>
  <object>
    <name>neg</name>
    <pose>NA</pose>
    <truncated>0</truncated>
    <difficult>0</difficult>
    <bndbox>
      <xmin>142</xmin>
      <ymin>85</ymin>
      <xmax>165</xmax>
      <ymax>117</ymax>
    </bndbox>
  </object>
  <object>
    <name>neg</name>
    <pose>NA</pose>
    <truncated>0</truncated>
    <difficult>0</difficult>
    <bndbox>
      <xmin>198</xmin>
      <ymin>107</ymin>
      <xmax>211</xmax>
      <ymax>124</ymax>
    </bndbox>
  </object>
  <object>
    <name>neg</name>
    <pose>NA</pose>
    <truncated>0</truncated>
    <difficult>0</difficult>
    <bndbox>
      <xmin>226</xmin>
      <ymin>109</ymin>
      <xmax>243</xmax>
      <ymax>131</ymax>
    </bndbox>
  </object>
  <object>
    <name>neg</name>
    <pose>NA</pose>
    <truncated>0</truncated>
    <difficult>0</difficult>
    <bndbox>
      <xmin>134</xmin>
      <ymin>147</ymin>
      <xmax>165</xmax>
      <ymax>189</ymax>
    </bndbox>
  </object>
</annotation>
