<annotation>
  <folder>NA</folder>
  <filename>2016-06-19-19-09-55_East_Houston_St__Ave_D.jpg</filename>
  <size>
    <width>352</width>
    <height>240</height>
    <depth>0</depth>
  </size>
  <segmented>0</segmented>
  <object>
    <name>pos</name>
    <pose>NA</pose>
    <truncated>0</truncated>
    <difficult>0</difficult>
    <bndbox>
      <xmin>17</xmin>
      <ymin>139</ymin>
      <xmax>42</xmax>
      <ymax>173</ymax>
    </bndbox>
  </object>
  <object>
    <name>pos</name>
    <pose>NA</pose>
    <truncated>0</truncated>
    <difficult>0</difficult>
    <bndbox>
      <xmin>9</xmin>
      <ymin>137</ymin>
      <xmax>27</xmax>
      <ymax>161</ymax>
    </bndbox>
  </object>
  <object>
    <name>neg</name>
    <pose>NA</pose>
    <truncated>0</truncated>
    <difficult>0</difficult>
    <bndbox>
      <xmin>161</xmin>
      <ymin>104</ymin>
      <xmax>175</xmax>
      <ymax>122</ymax>
    </bndbox>
  </object>
  <object>
    <name>neg</name>
    <pose>NA</pose>
    <truncated>0</truncated>
    <difficult>0</difficult>
    <bndbox>
      <xmin>205</xmin>
      <ymin>99</ymin>
      <xmax>221</xmax>
      <ymax>121</ymax>
    </bndbox>
  </object>
  <object>
    <name>neg</name>
    <pose>NA</pose>
    <truncated>0</truncated>
    <difficult>0</difficult>
    <bndbox>
      <xmin>169</xmin>
      <ymin>54</ymin>
      <xmax>186</xmax>
      <ymax>76</ymax>
    </bndbox>
  </object>
  <object>
    <name>neg</name>
    <pose>NA</pose>
    <truncated>0</truncated>
    <difficult>0</difficult>
    <bndbox>
      <xmin>228</xmin>
      <ymin>39</ymin>
      <xmax>241</xmax>
      <ymax>56</ymax>
    </bndbox>
  </object>
  <object>
    <name>neg</name>
    <pose>NA</pose>
    <truncated>0</truncated>
    <difficult>0</difficult>
    <bndbox>
      <xmin>296</xmin>
      <ymin>34</ymin>
      <xmax>308</xmax>
      <ymax>50</ymax>
    </bndbox>
  </object>
  <object>
    <name>neg</name>
    <pose>NA</pose>
    <truncated>0</truncated>
    <difficult>0</difficult>
    <bndbox>
      <xmin>197</xmin>
      <ymin>10</ymin>
      <xmax>211</xmax>
      <ymax>29</ymax>
    </bndbox>
  </object>
  <object>
    <name>neg</name>
    <pose>NA</pose>
    <truncated>0</truncated>
    <difficult>0</difficult>
    <bndbox>
      <xmin>121</xmin>
      <ymin>11</ymin>
      <xmax>135</xmax>
      <ymax>29</ymax>
    </bndbox>
  </object>
  <object>
    <name>neg</name>
    <pose>NA</pose>
    <truncated>0</truncated>
    <difficult>0</difficult>
    <bndbox>
      <xmin>70</xmin>
      <ymin>12</ymin>
      <xmax>81</xmax>
      <ymax>28</ymax>
    </bndbox>
  </object>
  <object>
    <name>neg</name>
    <pose>NA</pose>
    <truncated>0</truncated>
    <difficult>0</difficult>
    <bndbox>
      <xmin>24</xmin>
      <ymin>8</ymin>
      <xmax>36</xmax>
      <ymax>24</ymax>
    </bndbox>
  </object>
  <object>
    <name>neg</name>
    <pose>NA</pose>
    <truncated>0</truncated>
    <difficult>0</difficult>
    <bndbox>
      <xmin>14</xmin>
      <ymin>37</ymin>
      <xmax>28</xmax>
      <ymax>56</ymax>
    </bndbox>
  </object>
  <object>
    <name>neg</name>
    <pose>NA</pose>
    <truncated>0</truncated>
    <difficult>0</difficult>
    <bndbox>
      <xmin>21</xmin>
      <ymin>67</ymin>
      <xmax>32</xmax>
      <ymax>82</ymax>
    </bndbox>
  </object>
  <object>
    <name>neg</name>
    <pose>NA</pose>
    <truncated>0</truncated>
    <difficult>0</difficult>
    <bndbox>
      <xmin>111</xmin>
      <ymin>49</ymin>
      <xmax>121</xmax>
      <ymax>62</ymax>
    </bndbox>
  </object>
  <object>
    <name>neg</name>
    <pose>NA</pose>
    <truncated>0</truncated>
    <difficult>0</difficult>
    <bndbox>
      <xmin>136</xmin>
      <ymin>56</ymin>
      <xmax>147</xmax>
      <ymax>71</ymax>
    </bndbox>
  </object>
  <object>
    <name>neg</name>
    <pose>NA</pose>
    <truncated>0</truncated>
    <difficult>0</difficult>
    <bndbox>
      <xmin>167</xmin>
      <ymin>161</ymin>
      <xmax>185</xmax>
      <ymax>184</ymax>
    </bndbox>
  </object>
  <object>
    <name>neg</name>
    <pose>NA</pose>
    <truncated>0</truncated>
    <difficult>0</difficult>
    <bndbox>
      <xmin>249</xmin>
      <ymin>134</ymin>
      <xmax>262</xmax>
      <ymax>151</ymax>
    </bndbox>
  </object>
  <object>
    <name>neg</name>
    <pose>NA</pose>
    <truncated>0</truncated>
    <difficult>0</difficult>
    <bndbox>
      <xmin>280</xmin>
      <ymin>133</ymin>
      <xmax>294</xmax>
      <ymax>152</ymax>
    </bndbox>
  </object>
  <object>
    <name>neg</name>
    <pose>NA</pose>
    <truncated>0</truncated>
    <difficult>0</difficult>
    <bndbox>
      <xmin>259</xmin>
      <ymin>171</ymin>
      <xmax>278</xmax>
      <ymax>198</ymax>
    </bndbox>
  </object>
</annotation>
